scuwl_petebuffon/__init__.py
scuwl_petebuffon/scuwl.py
scuwl-1.2.dist-info/LICENSE
scuwl-1.2.dist-info/METADATA
scuwl-1.2.dist-info/WHEEL
scuwl-1.2.dist-info/entry_points.txt
scuwl-1.2.dist-info/top_level.txt
scuwl-1.2.dist-info/RECORD
