Metadata-Version: 2.1
Name: scuwl
Version: 1.2
Summary: SCuWl, Simple custom wordlist generator.
Home-page: https://github.com/petebuffon/scuwl
Author: Pete Buffon
Author-email: pabuffon@gmail.com
Project-URL: Bug Tracker, https://github.com/petebuffon/scuwl/issues
Classifier: Programming Language :: Python :: 3
Classifier: License :: OSI Approved :: MIT License
Classifier: Operating System :: OS Independent
Requires-Python: >=3.8
License-File: LICENSE
Requires-Dist: aiohttp (>=3.8.3)
Requires-Dist: bs4 (>=0.0.1)
Requires-Dist: lxml (>=4.9.1)
